coordination_network_toolkit/__init__.py
coordination_network_toolkit/__main__.py
coordination_network_toolkit/compute_networks.py
coordination_network_toolkit/database.py
coordination_network_toolkit/graph.py
coordination_network_toolkit/output.py
coordination_network_toolkit/preprocess.py
coordination_network_toolkit/similarity.py
coordination_network_toolkit/urls.py
coordination_network_toolkit-1.5.2.dist-info/LICENSE
coordination_network_toolkit-1.5.2.dist-info/METADATA
coordination_network_toolkit-1.5.2.dist-info/WHEEL
coordination_network_toolkit-1.5.2.dist-info/entry_points.txt
coordination_network_toolkit-1.5.2.dist-info/top_level.txt
coordination_network_toolkit-1.5.2.dist-info/RECORD
