Metadata-Version: 2.1
Name: coordination-network-toolkit
Version: 1.5.2
Summary: Tools for computing networks of coordinated behaviour on social media
Home-page: https://github.com/QUT-Digital-Observatory/coordination-network-toolkit
Author: Timothy Graham (Digital Media Research Centre, QUT) and QUT Digital Observatory
Author-email: digitalobservatory@qut.edu.au
License: MIT
Keywords: social_science social_media_analysis similarity_networks
Platform: UNKNOWN
Classifier: Programming Language :: Python :: 3
Classifier: License :: OSI Approved :: MIT License
Classifier: Operating System :: OS Independent
Classifier: Development Status :: 4 - Beta
Classifier: Environment :: Console
Classifier: Intended Audience :: Science/Research
Classifier: Topic :: Scientific/Engineering :: Information Analysis
Classifier: Topic :: Sociology
Requires-Python: >=3.6
Requires-Dist: urllib3
Requires-Dist: regex (>=2021.3.17)
Requires-Dist: requests
Requires-Dist: networkx (>=2.5)
Requires-Dist: twarc (>=2.4.0)
Provides-Extra: development
Requires-Dist: nox ; extra == 'development'
Requires-Dist: pytest ; extra == 'development'
Requires-Dist: pip-tools ; extra == 'development'
